<?xml version="1.0" encoding="UTF-8"?> <presentation id="ntfleetwo" ismobile="false" mboname="WORKORDER" version="6.0.0" whereclause="woclass='WORKORDER' and istask=0 and siteid='9030'"> <page id="mainrec" scroll="false"> <include controltoclone="single_pageHeader" id="INCLUDE-single_pageHeader"/> <clientarea id="clientarea"> <tabgroup format="carddeck" id="maintabs" style="form"> <tab default="true" id="results" label="List"> <table id="resultsTable" label="Vlootregie Werkorders" startempty="true"> <defaultvalue dataattribute="historyflag" defaulttype="query" id="1484660123374" value="0"/> <tablebody displayrowsperpage="15" filterable="true" filterexpanded="true" id="resultsTablebody"> <tablecol filterable="false" id="1484133598472" mxevent="toggledetailstate" mxevent_desc="Toon details" type="event"/> <tablecol applink="ntplusawo" dataattribute="WONUM" id="results_showlist_column2" menutype="normal"/> <tablecol dataattribute="DESCRIPTION" id="results_showlist_column12"/> <tablecol dataattribute="parent" id="results_showlist_column6"/> <tablecol dataattribute="reportdate" id="results_showlist_column8" lookup="datelookup"/> <tablecol dataattribute="assetnum" id="results_showlist_column1" lookup="asset"/> <tablecol dataattribute="ASSET.SERIALNUM" id="1484218657342" lookup="asset"/> <tablecol dataattribute="asset.TOPLEVELPARENT.serialnum" id="1484218537123" label="Stel"/> <tablecol dataattribute="worktype" id="results_showlist_column3" lookup="worktype"/> <tablecol dataattribute="pmnum" id="1484140982600" lookup="pm"/> <tablecol dataattribute="historyflag" id="1484660059656" label="Gesloten"/> <tablecol dataattribute="status" id="results_showlist_column5" lookup="valuelist"/> <tablecol dataattribute="wopriority" id="results_showlist_column4" lookup="valuelist"/> <tablecol dataattribute="NTWARNINGINTERVAL" id="1497433790165"/> <tablecol dataattribute="ntpmtolerance" id="results_showlist_column7"/> <tablecol dataattribute="ntvbt" id="results_showlist_column9" label="VBT"/> <tablecol dataattribute="NTQPROFIel" id="results_showlist_column10" lookup="valuelist"/> <tablecol dataattribute="targcompdate" id="results_showlist_column11" lookup="DATELOOKUP"/> <tablecol dataattribute="NTFLEETWO.category" id="results_showlist_column13" width="80"/> <tablecol dataattribute="NTFLEETWO.warningdate" id="results_showlist_column14" lookup="DATELOOKUP"/> <tablecol dataattribute="NTFLEETWO.overduedate" id="1484311184938" lookup="DATELOOKUP"/> <tablecol dataattribute="NTFLEETWO.historyflag" id="1484311183218" label="WO Gereed"/> <tablecol dataattribute="NTFLEETWO.REPORTDATE" id="1497433861696" lookup="DATELOOKUP"/> <tablecol dataattribute="NTFLEETWO.actfinish" id="results_showlist_column15" lookup="DATELOOKUP"/> </tablebody> <tabledetails id="resultsTabledetails"> <section id="ntfleetwo_section_details"> <sectionrow id="1484133365561"> <sectioncol id="1484133371316"> <section id="1484133381671"> <multiparttextbox dataattribute="NTFLEETWO.NTFLEETCONTROLDEF.CATCONDITION" descdataattribute="NTFLEETWO.NTFLEETCONTROLDEF.CATCONDITION.description" descinputmode="readonly" id="1484133396917" inputmode="readonly"/> <multilinetextbox columns="40" dataattribute="NTFLEETWO.NTFLEETCONTROLDEF.CATCONDITION.expression" id="1484133404012" rows="6"/> </section> </sectioncol> <sectioncol id="1484133375727"> <section id="1484133421749"> <multilinetextbox columns="40" dataattribute="NTFLEETWO.NTFLEETCONTROLDEF.WARNINGDATEQUERY" id="1484133432268" inputmode="readonly" rows="7"/> </section> </sectioncol> <sectioncol id="1484133365565"> <section id="1484133365565ads"> <multilinetextbox columns="40" dataattribute="NTFLEETWO.NTFLEETCONTROLDEF.OVERDUEDATEQUERY" id="1484133ads432268" inputmode="readonly" rows="7"/> </section> </sectioncol> </sectionrow> </section> </tabledetails> </table> </tab> </tabgroup> </clientarea> <include controltoclone="pageFooter" id="INCLUDE-pageFooter"/> </page> <configurationblock id="datastore_configurationblock"> </configurationblock> </presentation>